setup.py
bin/callysto-install-kernel
callysto.egg-info/PKG-INFO
callysto.egg-info/SOURCES.txt
callysto.egg-info/dependency_links.txt
callysto.egg-info/requires.txt
callysto.egg-info/top_level.txt
lib/__init__.py
lib/kernel.py
lib/magics.py
lib/utils.py
lib/renderers/__init__.py
lib/renderers/base.py
lib/renderers/core.py
lib/renderers/cytoscapejs.py
lib/renderers/graphviz.py
lib/renderers/vega.py
lib/renderers/visjs.py