Metadata-Version: 1.1
Name: callysto
Version: 0.2.3
Summary: Framework to create domain-specific kernels for the Jupyter platform
Home-page: https://github.com/ajmazurie/callysto
Author: Aurelien Mazurie
Author-email: ajmazurie@oenone.net
License: UNKNOWN
Download-URL: https://github.com/ajmazurie/callysto/archive/0.2.3.zip
Platform: UNKNOWN
Classifier: Development Status :: 4 - Beta
Classifier: Environment :: Web Environment
Classifier: Framework :: IPython
Classifier: Intended Audience :: Developers
Classifier: License :: OSI Approved :: MIT License
Classifier: Operating System :: OS Independent
Classifier: Programming Language :: Python :: 2.7
